productfeeds-0.11.1-py3.6-nspkg.pth
productfeeds/base.py
productfeeds/command.py
productfeeds/models.py
productfeeds/utils.py
productfeeds/importers/__init__.py
productfeeds/importers/awinapi.py
productfeeds/importers/base.py
productfeeds/importers/convertiserapi.py
productfeeds/importers/dummyapi.py
productfeeds/importers/webepartnersapi.py
productfeeds/storage/__init__.py
productfeeds/storage/base.py
productfeeds/storage/dummystorage.py
productfeeds/storage/mysqlstorage.py
productfeeds/test/__init__.py
productfeeds/test/importer_test.py
productfeeds/test/utils_test.py
productfeeds-0.11.1.dist-info/METADATA
productfeeds-0.11.1.dist-info/WHEEL
productfeeds-0.11.1.dist-info/entry_points.txt
productfeeds-0.11.1.dist-info/namespace_packages.txt
productfeeds-0.11.1.dist-info/top_level.txt
productfeeds-0.11.1.dist-info/RECORD
